{
  "start_urls": {
    "nowsports": "https://neesports.me/",
    "nowmetv": "https://neelive.com/",
    "tgx": [
      "torrentgalaxy.mx",
      "torrentgalaxy.to",
      "tgx.rs"
    ]
  },
  "tamil_blasters": {
    "homepage": "https://www.1tamilblasters.net",
    "catalogs": {
      "english": {
        "tcrip": "52-english-movies-hdcam-dvdscr-predvd",
        "hdrip": "53-english-movies-hdrips-bdrips-dvdrips",
        "series": "92-english-web-series-tv-shows"
      }
    }
  },
  "tamilmv": {
    "homepage": "https://www.1tamilmv.com",
    "catalogs": {
      "english": {
        "tcrip": "46-predvd-dvdscr-cam-tc",
        "hdrip": [
          "49-web-hd-itunes-hd-bluray",
          "50-hd-rips-dvd-rips-br-rips"
        ],
        "series": "55-web-series-tv-shows"
      }
    },
    "supported_search_forums": {
      "46-predvd-dvdscr-cam-tc": {
        "language": "english",
        "media_type": "tcrip"
      },
      "49-web-hd-itunes-hd-bluray": {
        "language": "english",
        "media_type": "hdrip"
      },
      "50-hd-rips-dvd-rips-br-rips": {
        "language": "english",
        "media_type": "hdrip"
      },
      "55-web-series-tv-shows": {
        "language": "english",
        "media_type": "series"
      }
    }
  },
  "dlhd": {
    "channels_url": "https://daddylive.dad/24-7-channels.php",
    "channel_url": "https://daddylive.dad/stream/stream-{channel_number}.php",
    "schedule_url": "https://daddylive.dad/schedule/schedule-generated.php",
    "server_lookup_url": "https://allupplay.xyz/server_lookup.php?channel_id={server_type}{channel_id}",
    "m3u8_base_url": "https://{server_key}new.newkso.ru/{server_key}/{server_type}{channel_id}/mono.m3u8",
    "key_url": "https://key.keylocking.ru",
    "referer": "https://allupplay.xyz/",
    "category_mapping": {
      "Tv Shows": "Other Sports",
      "Soccer": "Football",
      "Cricket": "Cricket",
      "Tennis": "Tennis",
      "Tennis ATP - AUSTRALIAN OPEN": "Tennis",
      "Tennis ATP DOUBLES - AUSTRALIAN OPEN": "Tennis",
      "Tennis WTA - AUSTRALIAN OPEN": "Tennis",
      "Tennis WTA DOUBLES - AUSTRALIAN OPEN": "Tennis",
      "Tennis ATP - FRENCH OPEN": "Tennis",
      "Tennis MIXED DOUBLES - AUSTRALIAN OPEN": "Tennis",
      "Motorsport": "Motor Sport",
      "Boxing": "Boxing",
      "MMA": "MMA",
      "Golf": "Golf",
      "Snooker": "Other Sports",
      "Am. Football": "American Football",
      "Athletics": "Athletics",
      "Aussie rules": "Aussie Rules",
      "Baseball": "Baseball",
      "Basketball": "Basketball",
      "Bowling": "Bowling",
      "Cycling": "Cycling",
      "Darts": "Dart",
      "Floorball": "Floorball",
      "Futsal": "Futsal",
      "Gymnastics": "Gymnastics",
      "Handball": "Handball",
      "Horse Racing": "Horse Racing",
      "Ice Hockey": "Hockey",
      "Lacrosse": "Lacrosse",
      "Netball": "Netball",
      "Rugby League": "Rugby/AFL",
      "Rugby Union": "Rugby/AFL",
      "Squash": "Squash",
      "Volleyball": "Volleyball",
      "GAA": "GAA",
      "Clubber": "Other Sports"
    }
  },
  "sport_video": {
    "categories": {
      "american_football": "https://www.sport-video.org.ua/americanfootball.html",
      "basketball": "https://www.sport-video.org.ua/basketball.html",
      "baseball": "https://www.sport-video.org.ua/baseball.html",
      "football": "https://www.sport-video.org.ua/football.html",
      "hockey": "https://www.sport-video.org.ua/hockey.html",
      "rugby": "https://www.sport-video.org.ua/rugby.html",
      "other_sports": "https://www.sport-video.org.ua/other.html"
    }
  }
}